austin_web/__init__.py
austin_web/__main__.py
austin_web/_figlet.py
austin_web/data.py
austin_web/html/__init__.py
austin_web/html/austin.svg
austin_web/html/austin_web.html
austin_web/html/duration.js
austin_web/html/flamegraph.js
austin_web/html/index.html
austin_web/html/main.css
austin_web/html/ui.html
austin_web/html/ui_static.html
austin_web/html/websocket.js
austin_web-0.3.0.dist-info/METADATA
austin_web-0.3.0.dist-info/WHEEL
austin_web-0.3.0.dist-info/entry_points.txt
austin_web-0.3.0.dist-info/licenses/LICENSE.md
austin_web-0.3.0.dist-info/RECORD
