Metadata-Version: 2.1
Name: austin-web
Version: 0.3.0
Summary: Flame graph web application for Austin
Project-URL: homepage, https://github.com/P403n1x87/austin-web
Project-URL: documentation, https://austin-web.readthedocs.io
Project-URL: repository, https://github.com/P403n1x87/austin-web
Project-URL: issues, https://github.com/P403n1x87/austin-web/issues
Author-email: "Gabriele N. Tornetta" <phoenix1987@gmail.com>
License-Expression: GPL-3.0-or-later
License-File: LICENSE.md
Keywords: development,performance,profiling,testing
Classifier: Development Status :: 5 - Production/Stable
Classifier: Intended Audience :: Developers
Classifier: License :: OSI Approved :: GNU General Public License v3 or later (GPLv3+)
Classifier: Programming Language :: Python :: 3.9
Classifier: Programming Language :: Python :: 3.10
Classifier: Programming Language :: Python :: 3.11
Classifier: Programming Language :: Python :: 3.12
Requires-Python: >=3.9
Requires-Dist: aiohttp~=3.6
Requires-Dist: austin-python~=1.7
Requires-Dist: halo~=0.0.29
